MANIFEST.in
README.rst
setup.py
wantFrom.py
docs/Makefile
docs/build/doctrees/environment.pickle
docs/build/doctrees/get.doctree
docs/build/doctrees/index.doctree
docs/build/doctrees/modules.doctree
docs/build/html/.buildinfo
docs/build/html/genindex.html
docs/build/html/get.html
docs/build/html/index.html
docs/build/html/modules.html
docs/build/html/objects.inv
docs/build/html/py-modindex.html
docs/build/html/search.html
docs/build/html/searchindex.js
docs/build/html/_sources/get.txt
docs/build/html/_sources/index.txt
docs/build/html/_sources/modules.txt
docs/build/html/_static/ajax-loader.gif
docs/build/html/_static/alabaster.css
docs/build/html/_static/basic.css
docs/build/html/_static/comment-bright.png
docs/build/html/_static/comment-close.png
docs/build/html/_static/comment.png
docs/build/html/_static/doctools.js
docs/build/html/_static/down-pressed.png
docs/build/html/_static/down.png
docs/build/html/_static/file.png
docs/build/html/_static/jquery-1.11.1.js
docs/build/html/_static/jquery.js
docs/build/html/_static/minus.png
docs/build/html/_static/plus.png
docs/build/html/_static/pygments.css
docs/build/html/_static/searchtools.js
docs/build/html/_static/underscore-1.3.1.js
docs/build/html/_static/underscore.js
docs/build/html/_static/up-pressed.png
docs/build/html/_static/up.png
docs/build/html/_static/websupport.js
docs/source/conf.py
docs/source/get.rst
docs/source/index.rst
docs/source/modules.rst
images/.DS_Store
images/photo.png
scripts/want
want/__init__.py
want/photo.py
want/utils.py
want.egg-info/PKG-INFO
want.egg-info/SOURCES.txt
want.egg-info/dependency_links.txt
want.egg-info/requires.txt
want.egg-info/top_level.txt