Metadata-Version: 1.0
Name: want
Version: 0.0.8
Summary: Download images from website.
Home-page: https://github.com/YogaPan/want
Author: YogaPan
Author-email: godhand1234567@gmail.com
License: UNKNOWN
Platform: UNKNOWN
